ontodoc/__init__.py
ontodoc/__main__.py
ontodoc/classes/Class.py
ontodoc/classes/Documentation.py
ontodoc/classes/Footer.py
ontodoc/classes/Generic.py
ontodoc/classes/Homepage.py
ontodoc/classes/JSONOntoDocEncoder.py
ontodoc/classes/Ontology.py
ontodoc/classes/Property.py
ontodoc/cli.py
ontodoc/generate_page.py
ontodoc/ontology_properties.py
ontodoc/templates/class.md
ontodoc/templates/footer.md
ontodoc/templates/homepage.md
ontodoc/templates/property.md
ontodoc/utils.py
ontodoc/version.py
ontodoc-0.0.5.dist-info/METADATA
ontodoc-0.0.5.dist-info/WHEEL
ontodoc-0.0.5.dist-info/entry_points.txt
ontodoc-0.0.5.dist-info/licenses/LICENCE.txt
ontodoc-0.0.5.dist-info/RECORD
