Metadata-Version: 2.4
Name: ontodoc
Version: 0.0.5
Summary: Generate easily your markdown documentation for any ontology
License-Expression: Apache-2.0
License-File: LICENCE.txt
Keywords: Ontology,rdflib,jinja2,documentation,markdown
Author: StephaneBranly
Author-email: stephanebranly.pro@gmail.com
Requires-Python: >=3.8.1
Classifier: Programming Language :: Python :: 3
Classifier: Programming Language :: Python :: 3.9
Classifier: Programming Language :: Python :: 3.10
Classifier: Programming Language :: Python :: 3.11
Classifier: Programming Language :: Python :: 3.12
Classifier: Programming Language :: Python :: 3.13
Classifier: Programming Language :: Python :: 3.14
Requires-Dist: jinja2 (>=3.1.6,<4.0.0)
Requires-Dist: rdflib (>=7.1.3,<8.0.0)
Project-URL: Source, https://github.com/StephaneBranly/ontodoc
Project-URL: Tracker, https://github.com/StephaneBranly/ontodoc/issues
